{
  "type": "FeatureCollection",
  "features": [
    {
      "type": "Feature",
      "properties": {
        "First": "Aaron",
        "Last": "Racicot",
        "IRC": "racicot",
        "City": "Langley",
        "State": "WA",
        "ZIP": 98260
      },
      "geometry": {
        "type": "Point",
        "coordinates": [
          -122.44211196899414,
          48.027475820552326
        ]
      }
    },
    {
      "type": "Feature",
      "properties": {
        "First": "Greg",
        "Last": "Corradini",
        "IRC": "sudobangbang",
        "City": "Seattle",
        "State": "WA",
        "ZIP": 98103
      },
      "geometry": {
        "type": "Point",
        "coordinates": [
          -122.35233306884764,
          47.656831742126535
        ]
      }
    },
    {
      "type": "Feature",
      "properties": {
        "First": "Sam",
        "Last": "Matthews",
        "IRC": "svmatthews",
        "City": "Seattle",
        "State": "WA",
        "ZIP": 98103
      },
      "geometry": {
        "type": "Point",
        "coordinates": [
          -122.330407,
          47.661587
        ]
      }
    },
    {
      "type": "Feature",
      "properties": {
        "First": "Jacob",
        "Last": "Lesser",
        "IRC": "jlesser",
        "City": "Bellingham",
        "State": "WA",
        "ZIP": 98225
      },
      "geometry": {
        "type": "Point",
        "coordinates": [
          -122.485714,
          48.733831
        ]
      }
    },
    {
      "type": "Feature",
      "properties": {
        "First": "Andrew",
        "Last": "Powers",
        "IRC": "powersa",
        "City": "Seattle",
        "State": "WA",
        "ZIP": 98109
      },
      "geometry": {
        "type": "Point",
        "coordinates": [
          -122.332722,
          47.621134
        ]
      }
    },
    {
      "type": "Feature",
      "properties": {
        "First": "Dane",
        "Last": "Springmeyer",
        "IRC": "springmeyer",
        "City": "Winthrop",
        "State": "WA",
        "ZIP": 98862
      },
      "geometry": {
        "type": "Point",
        "coordinates": [
          -120.18608,
          48.47810
        ]
      }
    },
    {
      "type": "Feature",
      "properties": {
	      "First": "Debbie",
        "Last": "Bull",
        "IRC": "thedeb",
        "City": "Seattle",
        "State": "WA",
        "ZIP": 98104},
      "geometry": {
        "type": "Point",
        "coordinates": [
          -122.33093172311783,
          47.59909712100294
        ]
      }
    },
    {
      "type": "Feature",
      "properties": {
	      "First": "Jonny",
        "Last": "Kemp",
        "IRC": "kempj2",
        "City": "Seattle",
        "State": "WA",
        "ZIP": 98104},
      "geometry": {
        "type": "Point",
        "coordinates": [
          -122.384248,
          47.666054
        ]
      }
    }
  ]
}
